atcdr/__init__.py
atcdr/download.py
atcdr/generate.py
atcdr/main.py
atcdr/markdown.py
atcdr/open.py
atcdr/test.py
atcdr/util/__init__.py
atcdr/util/cost.py
atcdr/util/execute.py
atcdr/util/filetype.py
atcdr/util/gpt.py
atcdr/util/problem.py
atcoderstudybooster-0.231.dist-info/METADATA
atcoderstudybooster-0.231.dist-info/WHEEL
atcoderstudybooster-0.231.dist-info/entry_points.txt
atcoderstudybooster-0.231.dist-info/RECORD
