Metadata-Version: 2.3
Name: AtCoderStudyBooster
Version: 0.231
Summary: A tool to download and manage AtCoder problems.
Project-URL: Homepage, https://github.com/yuta6/AtCoderStudyBooster
Author-email: yuta6 <46110512+yuta6@users.noreply.github.com>
License: MIT
Requires-Python: >=3.8
Requires-Dist: beautifulsoup4
Requires-Dist: fire
Requires-Dist: markdownify>=0.13.1
Requires-Dist: questionary>=2.0.1
Requires-Dist: requests
Requires-Dist: rich>=13.7.1
Requires-Dist: tiktoken
Requires-Dist: types-beautifulsoup4>=4.12.0.20240511
Requires-Dist: types-requests>=2.32.0.20240712
Requires-Dist: yfinance
